{
  "annotations": {
    "list": [
      {
        "builtIn": 1,
        "datasource": {
          "type": "grafana",
          "uid": "-- Grafana --"
        },
        "enable": true,
        "hide": true,
        "iconColor": "rgba(0, 211, 255, 1)",
        "name": "Annotations & Alerts",
        "type": "dashboard"
      }
    ]
  },
  "description": "March Work Status: where the work is right now at a glance. Per-profile work buckets (dispatchable / in-spawn / in-steward / waiting-for-merge / escalated / blocked / total) plus a service up/down row. No logs, no per-service RED. Backed by march_legate_slices{stage} (#220), the corrected march_legate_queue_dispatchable (#219), march_legate_queue_{blocked,total}, and the per-service heartbeat metrics.",
  "editable": true,
  "fiscalYearStartMonth": 0,
  "graphTooltip": 1,
  "links": [
    {
      "asDropdown": false,
      "icon": "external link",
      "tags": [],
      "targetBlank": false,
      "title": "Legate loop service",
      "type": "link",
      "url": "/d/march-legate"
    }
  ],
  "liveNow": false,
  "panels": [
    {
      "collapsed": false,
      "gridPos": {
        "h": 1,
        "w": 24,
        "x": 0,
        "y": 0
      },
      "id": 100,
      "panels": [],
      "title": "Services (everything green?)",
      "type": "row"
    },
    {
      "datasource": {
        "type": "prometheus",
        "uid": "prometheus"
      },
      "description": "Brood session-state + teardown service. UP when it has emitted heartbeats in the last 5m. Global (one shared host) \u2014 not filtered by profile.",
      "fieldConfig": {
        "defaults": {
          "color": {
            "mode": "thresholds"
          },
          "mappings": [
            {
              "type": "special",
              "options": {
                "match": "null",
                "result": {
                  "text": "DOWN",
                  "index": 0
                }
              }
            },
            {
              "type": "range",
              "options": {
                "from": 0,
                "to": 0,
                "result": {
                  "text": "DOWN",
                  "index": 1
                }
              }
            },
            {
              "type": "range",
              "options": {
                "from": 0.0001,
                "to": 1000000000,
                "result": {
                  "text": "UP",
                  "index": 2
                }
              }
            }
          ],
          "noValue": "DOWN",
          "thresholds": {
            "mode": "absolute",
            "steps": [
              {
                "color": "red",
                "value": null
              },
              {
                "color": "green",
                "value": 0.0001
              }
            ]
          },
          "unit": "short"
        },
        "overrides": []
      },
      "gridPos": {
        "h": 6,
        "w": 5,
        "x": 0,
        "y": 1
      },
      "id": 1,
      "options": {
        "colorMode": "background",
        "graphMode": "none",
        "justifyMode": "center",
        "orientation": "auto",
        "reduceOptions": {
          "calcs": [
            "lastNotNull"
          ],
          "fields": "",
          "values": false
        },
        "textMode": "value_and_name"
      },
      "pluginVersion": "12.2.1",
      "targets": [
        {
          "datasource": {
            "type": "prometheus",
            "uid": "prometheus"
          },
          "editorMode": "code",
          "expr": "sum(increase(march_brood_heartbeat_total[5m]))",
          "legendFormat": "Brood",
          "range": true,
          "refId": "A"
        }
      ],
      "title": "Brood",
      "type": "stat"
    },
    {
      "datasource": {
        "type": "prometheus",
        "uid": "prometheus"
      },
      "description": "Hatchery spawn service. UP when it has emitted heartbeats in the last 5m. Global (one shared host) \u2014 not filtered by profile.",
      "fieldConfig": {
        "defaults": {
          "color": {
            "mode": "thresholds"
          },
          "mappings": [
            {
              "type": "special",
              "options": {
                "match": "null",
                "result": {
                  "text": "DOWN",
                  "index": 0
                }
              }
            },
            {
              "type": "range",
              "options": {
                "from": 0,
                "to": 0,
                "result": {
                  "text": "DOWN",
                  "index": 1
                }
              }
            },
            {
              "type": "range",
              "options": {
                "from": 0.0001,
                "to": 1000000000,
                "result": {
                  "text": "UP",
                  "index": 2
                }
              }
            }
          ],
          "noValue": "DOWN",
          "thresholds": {
            "mode": "absolute",
            "steps": [
              {
                "color": "red",
                "value": null
              },
              {
                "color": "green",
                "value": 0.0001
              }
            ]
          },
          "unit": "short"
        },
        "overrides": []
      },
      "gridPos": {
        "h": 6,
        "w": 5,
        "x": 5,
        "y": 1
      },
      "id": 2,
      "options": {
        "colorMode": "background",
        "graphMode": "none",
        "justifyMode": "center",
        "orientation": "auto",
        "reduceOptions": {
          "calcs": [
            "lastNotNull"
          ],
          "fields": "",
          "values": false
        },
        "textMode": "value_and_name"
      },
      "pluginVersion": "12.2.1",
      "targets": [
        {
          "datasource": {
            "type": "prometheus",
            "uid": "prometheus"
          },
          "editorMode": "code",
          "expr": "sum(increase(march_hatchery_heartbeat_total[5m]))",
          "legendFormat": "Hatchery",
          "range": true,
          "refId": "A"
        }
      ],
      "title": "Hatchery",
      "type": "stat"
    },
    {
      "datasource": {
        "type": "prometheus",
        "uid": "prometheus"
      },
      "description": "Herald observation service. UP when it has emitted heartbeats in the last 5m. Global (one shared host) \u2014 not filtered by profile.",
      "fieldConfig": {
        "defaults": {
          "color": {
            "mode": "thresholds"
          },
          "mappings": [
            {
              "type": "special",
              "options": {
                "match": "null",
                "result": {
                  "text": "DOWN",
                  "index": 0
                }
              }
            },
            {
              "type": "range",
              "options": {
                "from": 0,
                "to": 0,
                "result": {
                  "text": "DOWN",
                  "index": 1
                }
              }
            },
            {
              "type": "range",
              "options": {
                "from": 0.0001,
                "to": 1000000000,
                "result": {
                  "text": "UP",
                  "index": 2
                }
              }
            }
          ],
          "noValue": "DOWN",
          "thresholds": {
            "mode": "absolute",
            "steps": [
              {
                "color": "red",
                "value": null
              },
              {
                "color": "green",
                "value": 0.0001
              }
            ]
          },
          "unit": "short"
        },
        "overrides": []
      },
      "gridPos": {
        "h": 6,
        "w": 5,
        "x": 10,
        "y": 1
      },
      "id": 3,
      "options": {
        "colorMode": "background",
        "graphMode": "none",
        "justifyMode": "center",
        "orientation": "auto",
        "reduceOptions": {
          "calcs": [
            "lastNotNull"
          ],
          "fields": "",
          "values": false
        },
        "textMode": "value_and_name"
      },
      "pluginVersion": "12.2.1",
      "targets": [
        {
          "datasource": {
            "type": "prometheus",
            "uid": "prometheus"
          },
          "editorMode": "code",
          "expr": "sum(increase(march_herald_heartbeat_total[5m]))",
          "legendFormat": "Herald",
          "range": true,
          "refId": "A"
        }
      ],
      "title": "Herald",
      "type": "stat"
    },
    {
      "datasource": {
        "type": "prometheus",
        "uid": "prometheus"
      },
      "description": "Legate loop liveness for the selected profile(s). UP while march_legate_loop_up = 1; absence/0 => DOWN.",
      "fieldConfig": {
        "defaults": {
          "color": {
            "mode": "thresholds"
          },
          "mappings": [
            {
              "type": "value",
              "options": {
                "0": {
                  "text": "DOWN",
                  "index": 0
                },
                "1": {
                  "text": "UP",
                  "index": 1
                }
              }
            },
            {
              "type": "special",
              "options": {
                "match": "null",
                "result": {
                  "text": "DOWN",
                  "index": 2
                }
              }
            }
          ],
          "noValue": "DOWN",
          "thresholds": {
            "mode": "absolute",
            "steps": [
              {
                "color": "red",
                "value": null
              },
              {
                "color": "green",
                "value": 1
              }
            ]
          },
          "unit": "short"
        },
        "overrides": []
      },
      "gridPos": {
        "h": 6,
        "w": 5,
        "x": 15,
        "y": 1
      },
      "id": 4,
      "options": {
        "colorMode": "background",
        "graphMode": "none",
        "justifyMode": "center",
        "orientation": "auto",
        "reduceOptions": {
          "calcs": [
            "lastNotNull"
          ],
          "fields": "",
          "values": false
        },
        "textMode": "value_and_name"
      },
      "pluginVersion": "12.2.1",
      "targets": [
        {
          "datasource": {
            "type": "prometheus",
            "uid": "prometheus"
          },
          "editorMode": "code",
          "expr": "max(march_legate_loop_up{profile=~\"$profile\"})",
          "legendFormat": "Legate loop",
          "range": true,
          "refId": "A"
        }
      ],
      "title": "Legate loop",
      "type": "stat"
    },
    {
      "datasource": {
        "type": "prometheus",
        "uid": "prometheus"
      },
      "description": "Castra interactive-session host. UP when it has emitted heartbeats in the last 5m. Global (one shared host) \u2014 not filtered by profile.",
      "fieldConfig": {
        "defaults": {
          "color": {
            "mode": "thresholds"
          },
          "mappings": [
            {
              "type": "special",
              "options": {
                "match": "null",
                "result": {
                  "text": "DOWN",
                  "index": 0
                }
              }
            },
            {
              "type": "range",
              "options": {
                "from": 0,
                "to": 0,
                "result": {
                  "text": "DOWN",
                  "index": 1
                }
              }
            },
            {
              "type": "range",
              "options": {
                "from": 0.0001,
                "to": 1000000000,
                "result": {
                  "text": "UP",
                  "index": 2
                }
              }
            }
          ],
          "noValue": "DOWN",
          "thresholds": {
            "mode": "absolute",
            "steps": [
              {
                "color": "red",
                "value": null
              },
              {
                "color": "green",
                "value": 0.0001
              }
            ]
          },
          "unit": "short"
        },
        "overrides": []
      },
      "gridPos": {
        "h": 6,
        "w": 4,
        "x": 20,
        "y": 1
      },
      "id": 5,
      "options": {
        "colorMode": "background",
        "graphMode": "none",
        "justifyMode": "center",
        "orientation": "auto",
        "reduceOptions": {
          "calcs": [
            "lastNotNull"
          ],
          "fields": "",
          "values": false
        },
        "textMode": "value_and_name"
      },
      "pluginVersion": "12.2.1",
      "targets": [
        {
          "datasource": {
            "type": "prometheus",
            "uid": "prometheus"
          },
          "editorMode": "code",
          "expr": "sum(increase(march_castra_heartbeat_total[5m]))",
          "legendFormat": "Castra",
          "range": true,
          "refId": "A"
        }
      ],
      "title": "Castra",
      "type": "stat"
    },
    {
      "collapsed": false,
      "gridPos": {
        "h": 1,
        "w": 24,
        "x": 0,
        "y": 7
      },
      "id": 200,
      "panels": [],
      "title": "Pending \u2014 queued work",
      "type": "row"
    },
    {
      "datasource": {
        "type": "prometheus",
        "uid": "prometheus"
      },
      "description": "Smithy dependency frontier ready to dispatch now \u2014 actionable layer-0 nodes minus in-flight/archived (march_legate_queue_dispatchable, #289). This is what the parallelism cap gates.",
      "fieldConfig": {
        "defaults": {
          "color": {
            "mode": "thresholds"
          },
          "mappings": [],
          "thresholds": {
            "mode": "absolute",
            "steps": [
              {
                "color": "green",
                "value": null
              }
            ]
          },
          "unit": "short"
        },
        "overrides": []
      },
      "gridPos": {
        "h": 6,
        "w": 8,
        "x": 0,
        "y": 8
      },
      "id": 201,
      "options": {
        "colorMode": "value",
        "graphMode": "area",
        "justifyMode": "auto",
        "orientation": "auto",
        "reduceOptions": {
          "calcs": [
            "lastNotNull"
          ],
          "fields": "",
          "values": false
        },
        "textMode": "auto"
      },
      "pluginVersion": "12.2.1",
      "targets": [
        {
          "datasource": {
            "type": "prometheus",
            "uid": "prometheus"
          },
          "editorMode": "code",
          "expr": "sum(march_legate_queue_dispatchable{profile=~\"$profile\"})",
          "legendFormat": "dispatchable",
          "range": true,
          "refId": "A"
        }
      ],
      "title": "Dispatchable",
      "type": "stat"
    },
    {
      "datasource": {
        "type": "prometheus",
        "uid": "prometheus"
      },
      "description": "Layer-1 pending items that cannot launch even with infinite parallelism because their dependencies are unmet (march_legate_queue_blocked).",
      "fieldConfig": {
        "defaults": {
          "color": {
            "mode": "thresholds"
          },
          "mappings": [],
          "thresholds": {
            "mode": "absolute",
            "steps": [
              {
                "color": "green",
                "value": null
              }
            ]
          },
          "unit": "short"
        },
        "overrides": []
      },
      "gridPos": {
        "h": 6,
        "w": 8,
        "x": 8,
        "y": 8
      },
      "id": 202,
      "options": {
        "colorMode": "value",
        "graphMode": "area",
        "justifyMode": "auto",
        "orientation": "auto",
        "reduceOptions": {
          "calcs": [
            "lastNotNull"
          ],
          "fields": "",
          "values": false
        },
        "textMode": "auto"
      },
      "pluginVersion": "12.2.1",
      "targets": [
        {
          "datasource": {
            "type": "prometheus",
            "uid": "prometheus"
          },
          "editorMode": "code",
          "expr": "sum(march_legate_queue_blocked{profile=~\"$profile\"})",
          "legendFormat": "blocked",
          "range": true,
          "refId": "A"
        }
      ],
      "title": "Blocked",
      "type": "stat"
    },
    {
      "datasource": {
        "type": "prometheus",
        "uid": "prometheus"
      },
      "description": "All outstanding tracked work we know of \u2014 dispatchable + blocked + deeper layers (march_legate_queue_total).",
      "fieldConfig": {
        "defaults": {
          "color": {
            "mode": "thresholds"
          },
          "mappings": [],
          "thresholds": {
            "mode": "absolute",
            "steps": [
              {
                "color": "green",
                "value": null
              }
            ]
          },
          "unit": "short"
        },
        "overrides": []
      },
      "gridPos": {
        "h": 6,
        "w": 8,
        "x": 16,
        "y": 8
      },
      "id": 203,
      "options": {
        "colorMode": "value",
        "graphMode": "area",
        "justifyMode": "auto",
        "orientation": "auto",
        "reduceOptions": {
          "calcs": [
            "lastNotNull"
          ],
          "fields": "",
          "values": false
        },
        "textMode": "auto"
      },
      "pluginVersion": "12.2.1",
      "targets": [
        {
          "datasource": {
            "type": "prometheus",
            "uid": "prometheus"
          },
          "editorMode": "code",
          "expr": "sum(march_legate_queue_total{profile=~\"$profile\"})",
          "legendFormat": "total",
          "range": true,
          "refId": "A"
        }
      ],
      "title": "Total remaining",
      "type": "stat"
    },
    {
      "collapsed": false,
      "gridPos": {
        "h": 1,
        "w": 24,
        "x": 0,
        "y": 14
      },
      "id": 210,
      "panels": [],
      "title": "Working \u2014 active resource",
      "type": "row"
    },
    {
      "datasource": {
        "type": "prometheus",
        "uid": "prometheus"
      },
      "description": "Slices with a codex worker running \u2014 queued or implementing (march_legate_slices stage hatchery-pending|implementing). Resource-heavy; counts toward the concurrency cap.",
      "fieldConfig": {
        "defaults": {
          "color": {
            "mode": "thresholds"
          },
          "mappings": [],
          "thresholds": {
            "mode": "absolute",
            "steps": [
              {
                "color": "green",
                "value": null
              }
            ]
          },
          "unit": "short"
        },
        "overrides": []
      },
      "gridPos": {
        "h": 6,
        "w": 8,
        "x": 0,
        "y": 15
      },
      "id": 211,
      "options": {
        "colorMode": "value",
        "graphMode": "area",
        "justifyMode": "auto",
        "orientation": "auto",
        "reduceOptions": {
          "calcs": [
            "lastNotNull"
          ],
          "fields": "",
          "values": false
        },
        "textMode": "auto"
      },
      "pluginVersion": "12.2.1",
      "targets": [
        {
          "datasource": {
            "type": "prometheus",
            "uid": "prometheus"
          },
          "editorMode": "code",
          "expr": "sum(march_legate_slices{stage=~\"hatchery-pending|implementing\", profile=~\"$profile\"})",
          "legendFormat": "in spawn",
          "range": true,
          "refId": "A"
        }
      ],
      "title": "In spawn",
      "type": "stat"
    },
    {
      "datasource": {
        "type": "prometheus",
        "uid": "prometheus"
      },
      "description": "Slices a steward session is actively driving \u2014 review fixes, conflicts, or failing checks (pr-open|pr-in-fix|pr-resolving-conflicts minus waiting-for-merge). Resource-heavy; counts toward the cap.",
      "fieldConfig": {
        "defaults": {
          "color": {
            "mode": "thresholds"
          },
          "mappings": [],
          "thresholds": {
            "mode": "absolute",
            "steps": [
              {
                "color": "green",
                "value": null
              }
            ]
          },
          "unit": "short"
        },
        "overrides": []
      },
      "gridPos": {
        "h": 6,
        "w": 8,
        "x": 8,
        "y": 15
      },
      "id": 212,
      "options": {
        "colorMode": "value",
        "graphMode": "area",
        "justifyMode": "auto",
        "orientation": "auto",
        "reduceOptions": {
          "calcs": [
            "lastNotNull"
          ],
          "fields": "",
          "values": false
        },
        "textMode": "auto"
      },
      "pluginVersion": "12.2.1",
      "targets": [
        {
          "datasource": {
            "type": "prometheus",
            "uid": "prometheus"
          },
          "editorMode": "code",
          "expr": "clamp_min(sum(march_legate_slices{stage=~\"pr-open|pr-in-fix|pr-resolving-conflicts\", profile=~\"$profile\"}) - sum(march_legate_slices_ready_to_merge{profile=~\"$profile\"}), 0)",
          "legendFormat": "in steward",
          "range": true,
          "refId": "A"
        }
      ],
      "title": "In steward",
      "type": "stat"
    },
    {
      "datasource": {
        "type": "prometheus",
        "uid": "prometheus"
      },
      "description": "Clean PRs parked awaiting a merge \u2014 checks pass, mergeable, no threads owed (march_legate_slices_ready_to_merge). Consumes no spawn/steward, so it does NOT count toward the cap.",
      "fieldConfig": {
        "defaults": {
          "color": {
            "mode": "thresholds"
          },
          "mappings": [],
          "thresholds": {
            "mode": "absolute",
            "steps": [
              {
                "color": "green",
                "value": null
              }
            ]
          },
          "unit": "short"
        },
        "overrides": []
      },
      "gridPos": {
        "h": 6,
        "w": 8,
        "x": 16,
        "y": 15
      },
      "id": 213,
      "options": {
        "colorMode": "value",
        "graphMode": "area",
        "justifyMode": "auto",
        "orientation": "auto",
        "reduceOptions": {
          "calcs": [
            "lastNotNull"
          ],
          "fields": "",
          "values": false
        },
        "textMode": "auto"
      },
      "pluginVersion": "12.2.1",
      "targets": [
        {
          "datasource": {
            "type": "prometheus",
            "uid": "prometheus"
          },
          "editorMode": "code",
          "expr": "sum(march_legate_slices_ready_to_merge{profile=~\"$profile\"})",
          "legendFormat": "waiting",
          "range": true,
          "refId": "A"
        }
      ],
      "title": "Waiting for merge",
      "type": "stat"
    },
    {
      "collapsed": false,
      "gridPos": {
        "h": 1,
        "w": 24,
        "x": 0,
        "y": 21
      },
      "id": 220,
      "panels": [],
      "title": "Escalation \u2014 needs attention",
      "type": "row"
    },
    {
      "datasource": {
        "type": "prometheus",
        "uid": "prometheus"
      },
      "description": "Slices escalated because the spawn failed before handing off to a steward \u2014 reason hatchery_dispatch_failed (march_legate_escalated). Auto-recovers within budget; then operator-only. The orphaned steward (if any) is culled automatically.",
      "fieldConfig": {
        "defaults": {
          "color": {
            "mode": "thresholds"
          },
          "mappings": [],
          "thresholds": {
            "mode": "absolute",
            "steps": [
              {
                "color": "green",
                "value": null
              },
              {
                "color": "red",
                "value": 1
              }
            ]
          },
          "unit": "short"
        },
        "overrides": []
      },
      "gridPos": {
        "h": 6,
        "w": 12,
        "x": 0,
        "y": 22
      },
      "id": 221,
      "options": {
        "colorMode": "value",
        "graphMode": "area",
        "justifyMode": "auto",
        "orientation": "auto",
        "reduceOptions": {
          "calcs": [
            "lastNotNull"
          ],
          "fields": "",
          "values": false
        },
        "textMode": "auto"
      },
      "pluginVersion": "12.2.1",
      "targets": [
        {
          "datasource": {
            "type": "prometheus",
            "uid": "prometheus"
          },
          "editorMode": "code",
          "expr": "sum(march_legate_escalated{reason=\"hatchery_dispatch_failed\", profile=~\"$profile\"})",
          "legendFormat": "spawn failed",
          "range": true,
          "refId": "A"
        }
      ],
      "title": "Spawn failed (never reached steward)",
      "type": "stat"
    },
    {
      "datasource": {
        "type": "prometheus",
        "uid": "prometheus"
      },
      "description": "Slices escalated for steward-stuck / judgement reasons \u2014 needs the legate agent or an operator (march_legate_escalated reason != hatchery_dispatch_failed).",
      "fieldConfig": {
        "defaults": {
          "color": {
            "mode": "thresholds"
          },
          "mappings": [],
          "thresholds": {
            "mode": "absolute",
            "steps": [
              {
                "color": "green",
                "value": null
              },
              {
                "color": "red",
                "value": 1
              }
            ]
          },
          "unit": "short"
        },
        "overrides": []
      },
      "gridPos": {
        "h": 6,
        "w": 12,
        "x": 12,
        "y": 22
      },
      "id": 222,
      "options": {
        "colorMode": "value",
        "graphMode": "area",
        "justifyMode": "auto",
        "orientation": "auto",
        "reduceOptions": {
          "calcs": [
            "lastNotNull"
          ],
          "fields": "",
          "values": false
        },
        "textMode": "auto"
      },
      "pluginVersion": "12.2.1",
      "targets": [
        {
          "datasource": {
            "type": "prometheus",
            "uid": "prometheus"
          },
          "editorMode": "code",
          "expr": "sum(march_legate_escalated{reason!=\"hatchery_dispatch_failed\", profile=~\"$profile\"})",
          "legendFormat": "escalated",
          "range": true,
          "refId": "A"
        }
      ],
      "title": "Escalated (steward stuck)",
      "type": "stat"
    },
    {
      "collapsed": false,
      "gridPos": {
        "h": 1,
        "w": 24,
        "x": 0,
        "y": 28
      },
      "id": 102,
      "panels": [],
      "title": "Work by stage over time",
      "type": "row"
    },
    {
      "datasource": {
        "type": "prometheus",
        "uid": "prometheus"
      },
      "description": "Slices by lifecycle stage over time (march_legate_slices{stage}), stacked. The total band height is the loop's non-archived slice count.",
      "fieldConfig": {
        "defaults": {
          "color": {
            "mode": "palette-classic"
          },
          "custom": {
            "axisBorderShow": false,
            "axisCenteredZero": false,
            "axisColorMode": "text",
            "axisLabel": "slices",
            "axisPlacement": "auto",
            "barAlignment": 0,
            "drawStyle": "line",
            "fillOpacity": 30,
            "gradientMode": "none",
            "hideFrom": {
              "legend": false,
              "tooltip": false,
              "viz": false
            },
            "lineInterpolation": "stepAfter",
            "lineWidth": 1,
            "pointSize": 5,
            "scaleDistribution": {
              "type": "linear"
            },
            "showPoints": "never",
            "spanNulls": false,
            "stacking": {
              "group": "A",
              "mode": "normal"
            },
            "thresholdsStyle": {
              "mode": "off"
            }
          },
          "mappings": [],
          "unit": "short"
        },
        "overrides": [
          {
            "matcher": {
              "id": "byName",
              "options": "escalated"
            },
            "properties": [
              {
                "id": "color",
                "value": {
                  "fixedColor": "red",
                  "mode": "fixed"
                }
              }
            ]
          }
        ]
      },
      "gridPos": {
        "h": 8,
        "w": 24,
        "x": 0,
        "y": 29
      },
      "id": 13,
      "options": {
        "legend": {
          "calcs": [
            "last",
            "max"
          ],
          "displayMode": "table",
          "placement": "right",
          "showLegend": true
        },
        "tooltip": {
          "mode": "multi",
          "sort": "desc"
        }
      },
      "pluginVersion": "12.2.1",
      "targets": [
        {
          "datasource": {
            "type": "prometheus",
            "uid": "prometheus"
          },
          "editorMode": "code",
          "expr": "sum by (stage) (march_legate_slices{profile=~\"$profile\"})",
          "legendFormat": "{{stage}}",
          "range": true,
          "refId": "A"
        }
      ],
      "title": "Slices by stage over time",
      "type": "timeseries"
    }
  ],
  "refresh": "30s",
  "schemaVersion": 39,
  "tags": [
    "march",
    "work-status",
    "observability"
  ],
  "templating": {
    "list": [
      {
        "current": {},
        "datasource": {
          "type": "prometheus",
          "uid": "prometheus"
        },
        "definition": "label_values(march_legate_loop_heartbeats_total, profile)",
        "includeAll": true,
        "allValue": ".*",
        "label": "profile",
        "multi": true,
        "name": "profile",
        "options": [],
        "query": {
          "query": "label_values(march_legate_loop_heartbeats_total, profile)",
          "refId": "PrometheusVariableQueryEditor-VariableQuery"
        },
        "refresh": 2,
        "regex": "",
        "type": "query"
      }
    ]
  },
  "time": {
    "from": "now-6h",
    "to": "now"
  },
  "timepicker": {},
  "timezone": "",
  "title": "March \u2014 Work Status",
  "uid": "march-work-status",
  "version": 1,
  "weekStart": ""
}